my_first_pypi_package_paiky/hello.py
my_first_pypi_package_paiky/py.typed
my_first_pypi_package_paiky-6.0.0.dist-info/METADATA
my_first_pypi_package_paiky-6.0.0.dist-info/WHEEL
my_first_pypi_package_paiky-6.0.0.dist-info/RECORD
