Metadata-Version: 2.4
Name: my_first_pypi_package_paiky
Version: 6.0.0
Summary: Made with love by Constructor
Author: paiky
Author-email: dev-miguel-mendez@proton.me
Requires-Python: >=3.12
Classifier: Programming Language :: Python :: 3
Classifier: Programming Language :: Python :: 3.12
Classifier: Programming Language :: Python :: 3.13
Classifier: Programming Language :: Python :: 3.14
